{
    "ghcide-nix": {
        "ref": "master",
        "repo": "https://code.devalot.com/pjones/ghcide-nix.git",
        "rev": "6ebbfcb233f2bfad4dfd03d964013096ea142750",
        "type": "git"
    },
    "niv": {
        "branch": "master",
        "description": "Easy dependency management for Nix projects",
        "homepage": "https://github.com/nmattia/niv",
        "owner": "nmattia",
        "repo": "niv",
        "rev": "f73bf8d584148677b01859677a63191c31911eae",
        "sha256": "0jlmrx633jvqrqlyhlzpvdrnim128gc81q5psz2lpp2af8p8q9qs",
        "type": "tarball",
        "url": "https://github.com/nmattia/niv/archive/f73bf8d584148677b01859677a63191c31911eae.tar.gz",
        "url_template": "https://github.com/<owner>/<repo>/archive/<rev>.tar.gz"
    },
    "nix-hs": {
        "ref": "next",
        "repo": "https://code.devalot.com/open/nix-hs.git",
        "rev": "b267b7dff1e83909e537b5e9af7de0975caf112c",
        "type": "git"
    },
    "nixpkgs": {
        "branch": "nixos-20.03",
        "description": "A read-only mirror of NixOS/nixpkgs tracking the released channels. Send issues and PRs to",
        "homepage": "https://github.com/NixOS/nixpkgs",
        "owner": "NixOS",
        "repo": "nixpkgs-channels",
        "rev": "9137f05564eb50cc6f7042039aa9549a2e6e2340",
        "sha256": "0yh2fnywhiyhzrkdlccp0l3bmdrqj0y1gysln6x7xfl2zj3aij7z",
        "type": "tarball",
        "url": "https://github.com/NixOS/nixpkgs-channels/archive/9137f05564eb50cc6f7042039aa9549a2e6e2340.tar.gz",
        "url_template": "https://github.com/<owner>/<repo>/archive/<rev>.tar.gz"
    },
    "ormolu": {
        "branch": "master",
        "description": "A formatter for Haskell source code",
        "homepage": null,
        "owner": "tweag",
        "repo": "ormolu",
        "rev": "3fbc130a0962ab236d87711beae1895d84a68362",
        "sha256": "1gfdc5rc9jgwkx4y7gfqasl95nxkpmkgwj3489s3n9ws88dfragw",
        "type": "tarball",
        "url": "https://github.com/tweag/ormolu/archive/3fbc130a0962ab236d87711beae1895d84a68362.tar.gz",
        "url_template": "https://github.com/<owner>/<repo>/archive/<rev>.tar.gz"
    },
    "validation-selective": {
        "branch": "master",
        "description": "💂‍♂️ Lightweight pure validation based on Applicative and Selective functors",
        "homepage": "https://kowainik.github.io/projects/validation-selective",
        "owner": "kowainik",
        "repo": "validation-selective",
        "rev": "5b46cd4810bbaa09b704062ebbfa2bb47137425d",
        "sha256": "0jjf882pq39ly29ikngkiz4zxqwkzv85m2rl37j5gcd0ywg3dcpi",
        "type": "tarball",
        "url": "https://github.com/kowainik/validation-selective/archive/5b46cd4810bbaa09b704062ebbfa2bb47137425d.tar.gz",
        "url_template": "https://github.com/<owner>/<repo>/archive/<rev>.tar.gz"
    }
}
